stegonosaurus/__init__.py
stegonosaurus/stegoexceptions.py
stegonosaurus/stegofunctions.py
stegonosaurus/stegoutils.py
stegonosaurus-1.2.3.dist-info/METADATA
stegonosaurus-1.2.3.dist-info/WHEEL
stegonosaurus-1.2.3.dist-info/top_level.txt
stegonosaurus-1.2.3.dist-info/RECORD
