Metadata-Version: 2.1
Name: stegonosaurus
Version: 1.2.3
Summary: Stegonography utilities
Home-page: https://github.com/Geada734/stegonosaurus
Author: Geada734
License: MIT
Keywords: steganography
Classifier: Development Status :: 5 - Production/Stable
Classifier: Intended Audience :: Education
Classifier: License :: OSI Approved :: MIT License
Classifier: Programming Language :: Python :: 3
